CMakeLists.txt
Config.cmake.in
LICENSE
MANIFEST.in
README.md
setup.cfg
setup.py
cmake/DownloadAllTheThings.cmake
cmake/FindCcache.cmake
cmake/FindYamlCpp.cmake
cmake/Findrapidjson.cmake
cmake/GetVersionFromFile.cmake
python/README.md
python/kotki/CMakeLists.txt
python/kotki/kotki-py.cpp
python/kotki/kotki-py.h
python/kotki.egg-info/PKG-INFO
python/kotki.egg-info/SOURCES.txt
python/kotki.egg-info/dependency_links.txt
python/kotki.egg-info/entry_points.txt
python/kotki.egg-info/not-zip-safe
python/kotki.egg-info/requires.txt
python/kotki.egg-info/top_level.txt
python/kotki_cli/__init__.py
python/kotki_web/run.py
python/kotki_web/settings.py
python/kotki_web/kweb/__init__.py
python/kotki_web/kweb/constants.py
python/kotki_web/kweb/routes.py
python/kotki_web/kweb/static/favicon.ico
python/kotki_web/kweb/static/style.css
python/kotki_web/kweb/templates/index.html
src/BERGAMOT_VERSION
src/CMakeLists.txt
src/README.md
src/.dev/README.md
src/.dev/generate_ssplit_bundle.py
src/.dev/print.js
src/.dev/urls.js
src/demo/kotki-srt.cpp
src/demo/kotki.cpp
src/kotki/aligned.h
src/kotki/annotation.cpp
src/kotki/annotation.h
src/kotki/batch.cpp
src/kotki/batch.h
src/kotki/batching_pool.cpp
src/kotki/batching_pool.h
src/kotki/byte_array_util.cpp
src/kotki/byte_array_util.h
src/kotki/cache.h
src/kotki/definitions.h
src/kotki/kotki.cpp
src/kotki/kotki.h
src/kotki/lang.cpp
src/kotki/lang.h
src/kotki/nb_prefix.h
src/kotki/parser.cpp
src/kotki/parser.h
src/kotki/project_version.h.in
src/kotki/quality_estimator.cpp
src/kotki/quality_estimator.h
src/kotki/request.cpp
src/kotki/request.h
src/kotki/response.cpp
src/kotki/response.h
src/kotki/response_builder.cpp
src/kotki/response_builder.h
src/kotki/response_options.h
src/kotki/text_processor.cpp
src/kotki/text_processor.h
src/kotki/translation_model.cpp
src/kotki/translation_model.h
src/kotki/utils.h
src/kotki/vocabs.h
src/kotki/xh_scanner.cpp
src/kotki/xh_scanner.h