Metadata-Version: 2.1
Name: kotki
Version: 0.6.1
Summary: Translate text locally on your machine.
Home-page: https://github.com/kroketio/kotki/
Author: Kroket Ltd.
Author-email: code@kroket.io
Project-URL: Bug Reports, https://github.com/kroketio/kotki/issues
Project-URL: Source, https://github.com/kroketio/kotki/
Classifier: Development Status :: 4 - Beta
Classifier: Intended Audience :: Developers
Classifier: Topic :: Software Development :: Build Tools
Classifier: License :: OSI Approved :: Mozilla Public License 2.0 (MPL 2.0)
Classifier: Programming Language :: Python :: 3
Classifier: Programming Language :: Python :: 3.6
Classifier: Programming Language :: Python :: 3.7
Classifier: Programming Language :: Python :: 3.8
Classifier: Programming Language :: Python :: 3.9
Classifier: Programming Language :: Python :: 3.10
Classifier: Programming Language :: Python :: 3 :: Only
Requires-Python: >=3.6
Provides-Extra: test
License-File: LICENSE
